mdapisp/.DS_Store
mdapisp/__init__.py
mdapisp/database.py
mdapisp/main.py
mdapisp/requirements.txt
mdapisp-0.1.1a3.dist-info/entry_points.txt
mdapisp-0.1.1a3.dist-info/WHEEL
mdapisp-0.1.1a3.dist-info/METADATA
mdapisp-0.1.1a3.dist-info/RECORD
