Metadata-Version: 2.1
Name: mdapisp
Version: 0.1.1a3
Summary: simple api for Make Data API Server Project
Author: Minseong Kim
Requires-Python: >=3.7.3,<4.0.0
Classifier: Programming Language :: Python :: 3
Classifier: Programming Language :: Python :: 3.8
Classifier: Programming Language :: Python :: 3.9
Requires-Dist: aiocache (>=0.11.1,<0.12.0)
Requires-Dist: aiosqlite (>=0.17.0,<0.18.0)
Requires-Dist: databases (>=0.4.2,<0.5.0)
Requires-Dist: fastapi (>=0.63.0,<0.64.0)
Requires-Dist: pandas (>=1.2.3,<2.0.0)
Requires-Dist: pytest (>=6.2.2,<7.0.0)
Requires-Dist: python-multipart (>=0.0.5,<0.0.6)
Requires-Dist: sqlalchemy (>=1.4.0,<2.0.0)
Requires-Dist: typer[all] (>=0.3.2,<0.4.0)
Requires-Dist: uvicorn (>=0.13.4,<0.14.0)
